Metadata-Version: 2.1
Name: kgitest
Version: 0.0.1
Summary: Test project
Author: KGI
Author-email: Teste@kgi.com
License-File: LICENSE
